Metadata-Version: 2.1
Name: Flask-Shell2HTTP
Version: 1.9.1
Summary: A minimalist REST API wrapper for python's subprocess API.
Home-page: https://github.com/eshaan7/flask-shell2http
Author: Eshaan Bansal
Author-email: eshaan7bansal@gmail.com
License: BSD
Project-URL: Documentation, https://github.com/eshaan7/flask-shell2http
Project-URL: Funding, https://www.paypal.me/eshaanbansal
Project-URL: Source, https://github.com/eshaan7/flask-shell2http
Project-URL: Tracker, https://github.com/eshaan7/flask-shell2http/issues
Keywords: flask shell2http subprocess python
Platform: any
Classifier: Environment :: Web Environment
Classifier: Intended Audience :: Developers
Classifier: Operating System :: OS Independent
Classifier: License :: OSI Approved :: BSD License
Classifier: Programming Language :: Python :: 3
Classifier: Programming Language :: Python :: 3.6
Classifier: Programming Language :: Python :: 3.7
Classifier: Programming Language :: Python :: 3.8
Classifier: Programming Language :: Python :: 3.9
Classifier: Programming Language :: Python :: 3.10
Classifier: Topic :: Internet :: WWW/HTTP :: Dynamic Content
Classifier: Topic :: Software Development :: Libraries :: Python Modules
Requires-Python: >= 3.6
Provides-Extra: test
License-File: LICENSE
